airflow_serde_polars/__init__.py
airflow_serde_polars/main.py
airflow_serde_polars/dump/__init__.py
airflow_serde_polars/dump/v1.py
airflow_serde_polars/dump/v2.py
airflow_serde_polars/load/__init__.py
airflow_serde_polars/load/v1.py
airflow_serde_polars/load/v2.py
airflow_serde_polars/utils/__init__.py
airflow_serde_polars/utils/parse.py
airflow/serialization/serializers/polars.py
airflow_serde_polars-0.2.0.dist-info/METADATA
airflow_serde_polars-0.2.0.dist-info/WHEEL
airflow_serde_polars-0.2.0.dist-info/licenses/LICENSE
airflow_serde_polars-0.2.0.dist-info/RECORD
