Metadata-Version: 2.3
Name: airflow-serde-polars
Version: 0.2.0
Summary: Apache Airflow serialization plugin using Polars
Project-URL: Repository, https://github.com/phi-friday/airflow-serde-polars
Author-email: phi <phi.friday@gmail.com>
License-File: LICENSE
Classifier: Development Status :: 4 - Beta
Classifier: Programming Language :: Python :: 3
Classifier: Programming Language :: Python :: 3.8
Classifier: Programming Language :: Python :: 3.9
Classifier: Programming Language :: Python :: 3.10
Classifier: Programming Language :: Python :: 3.11
Classifier: Programming Language :: Python :: 3.12
Classifier: Programming Language :: Python :: Implementation :: CPython
Requires-Python: >=3.8
Requires-Dist: polars[pyarrow]>=1.0.0
Provides-Extra: test
Requires-Dist: apache-airflow>=2.8.1; extra == 'test'
Requires-Dist: pytest>=8.3.2; extra == 'test'
